ec2ctl/__init__.py
ec2ctl/cli.py
ec2ctl/config.py
ec2ctl/ec2.py
ec2ctl/exceptions.py
ec2ctl-0.1.1.dist-info/METADATA
ec2ctl-0.1.1.dist-info/WHEEL
ec2ctl-0.1.1.dist-info/entry_points.txt
ec2ctl-0.1.1.dist-info/top_level.txt
ec2ctl-0.1.1.dist-info/RECORD
