Metadata-Version: 2.4
Name: ec2ctl
Version: 0.1.1
Classifier: Programming Language :: Python :: 3
Classifier: License :: OSI Approved :: MIT License
Classifier: Operating System :: OS Independent
Requires-Dist: click
Requires-Dist: boto3
Requires-Dist: PyYAML
Dynamic: classifier
Dynamic: description
Dynamic: description-content-type
Dynamic: requires-dist
